agri_tech/__init__.py
agri_tech/agri_tech.py
agri_tech/cli.py
agri_tech/filename.txt
agri_tech/data/filename.txt
agri_tech-0.1.9.dist-info/.ipynb_checkpoints/PKG-INFO-checkpoint
agri_tech-0.1.9.dist-info/.ipynb_checkpoints/dependency_links-checkpoint.txt
agri_tech-0.1.9.dist-info/.ipynb_checkpoints/top_level-checkpoint.txt
agri_tech-0.1.9.dist-info/AUTHORS.rst
agri_tech-0.1.9.dist-info/LICENSE
agri_tech-0.1.9.dist-info/METADATA
agri_tech-0.1.9.dist-info/WHEEL
agri_tech-0.1.9.dist-info/entry_points.txt
agri_tech-0.1.9.dist-info/top_level.txt
agri_tech-0.1.9.dist-info/RECORD
