Metadata-Version: 2.1
Name: agri-tech
Version: 0.1.9
Summary: Loading and using Lidardata
Home-page: https://github.com/Kibika/Agritech/agri_tech
Author: Stella Kibika
Author-email: steshykibika@gmail.com
License: MIT license
Keywords: agri_tech
Platform: UNKNOWN
Classifier: Development Status :: 2 - Pre-Alpha
Classifier: Intended Audience :: Developers
Classifier: License :: OSI Approved :: MIT License
Classifier: Natural Language :: English
Classifier: Programming Language :: Python :: 3
Classifier: Programming Language :: Python :: 3.6
Classifier: Programming Language :: Python :: 3.7
Classifier: Programming Language :: Python :: 3.8
Requires-Python: >=3.6
License-File: LICENSE
License-File: AUTHORS.rst
Requires-Dist: PDAL
Requires-Dist: GDAL
Requires-Dist: scipy
Requires-Dist: rasterio
Requires-Dist: geopandas
Requires-Dist: requests
Requires-Dist: shapely
Requires-Dist: ipywidgets
